langchain_nmret/__init__.py
langchain_nmret/nmret.py
langchain_nmret-0.1.3.dist-info/METADATA
langchain_nmret-0.1.3.dist-info/WHEEL
langchain_nmret-0.1.3.dist-info/licenses/LICENSE
langchain_nmret-0.1.3.dist-info/RECORD
